[
  {
    "Title": "Piso en Simancas, Madrid",
    "Price": "167.892€",
    "Url": "/inmueble/102240340/",
    "Bedrooms": "2 hab.",
    "Area": "47 m²",
    "Description": "HASTA 100% DE FINANCIACIÓN PARA FUNCIONARIOS Y PERSONAL LABORAL PÚBLICO.\n100% HOME RED INMOBILIARIA vende piso en Madrid, zona Canillejas.\nLa vivienda cuenta con una superficie de 47m², distribuidos en cocina, salon comedor, dos dormitorios y un baño.\nVivienda con orientación Este para reforma integral.\nFinca con ascen"
  },
  {
    "Title": "Piso en calle de la Colonia Erillas, San Diego, Madrid",
    "Price": "132.266€",
    "Url": "/inmueble/105354129/",
    "Bedrooms": "3 hab.",
    "Area": "96 m²",
    "Description": "Oportunidad Única de Inversión - Activo Inmobiliario\nREFERENCIA: 18090\n[Auctree. com/auction/18090]\nHoy os presentamos una excelente oportunidad de inversión que ofrece un potencial significativo de revalorización y rentabilidad.\nAuctree es la plataforma líder en España para inversores inmobiliarios. Con nosotros"
  },
  {
    "Title": "Piso en paseo de los artilleros, 2, Ambroz, Madrid",
    "Price": "159.000€",
    "Url": "/inmueble/33211233/",
    "Bedrooms": "2 hab.",
    "Area": "55 m²",
    "Description": ""
  }
]